LICENSE
README.md
setup.py
inegi_explorer/__init__.py
inegi_explorer/config.py
inegi_explorer/explorer.py
inegi_explorer.egg-info/PKG-INFO
inegi_explorer.egg-info/SOURCES.txt
inegi_explorer.egg-info/dependency_links.txt
inegi_explorer.egg-info/requires.txt
inegi_explorer.egg-info/top_level.txt
inegi_explorer/nodes/__init__.py
inegi_explorer/nodes/indicator_node.py
inegi_explorer/nodes/node.py
inegi_explorer/nodes/subject_node.py