Metadata-Version: 2.1
Name: inegi-explorer
Version: 0.1.1
Summary: A Python package for exploring and fetching INEGI data without requiring an API key.
Home-page: https://github.com/FabioSol/INEGIExplorer
Author: Fabio Sol
Author-email: fabioso2231@gmail.com
Classifier: Development Status :: 3 - Alpha
Classifier: Programming Language :: Python :: 3.11
Classifier: License :: OSI Approved :: MIT License
Classifier: Operating System :: OS Independent
Requires-Python: >=3.11
License-File: LICENSE
